jitxlib/jlcpcb/JLC04161H_1080.py
jitxlib/jlcpcb/JLC04161H_7628.py
jitxlib/jlcpcb/JLC06161H_7628.py
jitxlib/jlcpcb/__init__.py
jitxlib/jlcpcb/materials.py
jitxlib/jlcpcb/rules.py
jitxlib/jlcpcb/vias.py
jitxlib_jlcpcb-1.0.0.dist-info/METADATA
jitxlib_jlcpcb-1.0.0.dist-info/WHEEL
jitxlib_jlcpcb-1.0.0.dist-info/RECORD
