Metadata-Version: 2.4
Name: jitxlib-jlcpcb
Version: 1.0.0
Requires-Python: >=3.12
Requires-Dist: jitx<5,>=4.0.0
Requires-Dist: jitxlib-standard<5,>=4.0.0
